patpy/__init__.py
patpy/pl/__init__.py
patpy/pl/basic.py
patpy/pp/__init__.py
patpy/pp/basic.py
patpy/tl/__init__.py
patpy/tl/_types.py
patpy/tl/evaluation.py
patpy/tl/gloscope.R
patpy/tl/persistence.py
patpy/tl/sample_representation.py
patpy-0.11.2.dist-info/METADATA
patpy-0.11.2.dist-info/WHEEL
patpy-0.11.2.dist-info/licenses/LICENSE
patpy-0.11.2.dist-info/RECORD
