Metadata-Version: 2.4
Name: patpy
Version: 0.11.2
Summary: A toolbox for patient or sample representation from single-cell data
Project-URL: Documentation, https://patpy.readthedocs.io/
Project-URL: Homepage, https://github.com/lueckenlab/patpy
Project-URL: Source, https://github.com/lueckenlab/patpy
Author: Vladimir Shitov
Maintainer-email: Vladimir Shitov <vladimir.shitov@helmholtz-munich.de>
License: BSD 3-Clause License
License-File: LICENSE
Classifier: Programming Language :: Python :: 3 :: Only
Classifier: Programming Language :: Python :: 3.10
Classifier: Programming Language :: Python :: 3.11
Classifier: Programming Language :: Python :: 3.12
Classifier: Programming Language :: Python :: 3.13
Requires-Python: >=3.10
Requires-Dist: anndata>=0.8
Requires-Dist: ehrapy
Requires-Dist: gudhi
Requires-Dist: matplotlib>=3.6
Requires-Dist: numpy>=1.23
Requires-Dist: opentsne>=0.6
Requires-Dist: pandas>=1.5
Requires-Dist: plottable
Requires-Dist: scipy>=1.10
Requires-Dist: seaborn>=0.12
Requires-Dist: session-info2
Provides-Extra: dev
Requires-Dist: pre-commit; extra == 'dev'
Requires-Dist: twine>=4.0.2; extra == 'dev'
Provides-Extra: diffusionemd
Requires-Dist: diffusionemd; extra == 'diffusionemd'
Requires-Dist: phate>=1.0.11; extra == 'diffusionemd'
Provides-Extra: doc
Requires-Dist: docutils!=0.18.*,!=0.19.*,>=0.8; extra == 'doc'
Requires-Dist: ipykernel; extra == 'doc'
Requires-Dist: ipython; extra == 'doc'
Requires-Dist: myst-nb>=1.1; extra == 'doc'
Requires-Dist: nbsphinx; extra == 'doc'
Requires-Dist: pandas; extra == 'doc'
Requires-Dist: setuptools; extra == 'doc'
Requires-Dist: sphinx-autodoc-typehints; extra == 'doc'
Requires-Dist: sphinx-book-theme>=1; extra == 'doc'
Requires-Dist: sphinx-copybutton; extra == 'doc'
Requires-Dist: sphinx-design; extra == 'doc'
Requires-Dist: sphinx-tabs; extra == 'doc'
Requires-Dist: sphinx>=8.1; extra == 'doc'
Requires-Dist: sphinxcontrib-bibtex>=1; extra == 'doc'
Requires-Dist: sphinxext-opengraph; extra == 'doc'
Provides-Extra: gloscope-py-cpu
Requires-Dist: pynndescent; extra == 'gloscope-py-cpu'
Provides-Extra: gloscope-py-gpu
Requires-Dist: cuml; extra == 'gloscope-py-gpu'
Requires-Dist: cupy; extra == 'gloscope-py-gpu'
Provides-Extra: mrvi
Requires-Dist: scvi-tools>=1.2; extra == 'mrvi'
Requires-Dist: torch>=1.13; extra == 'mrvi'
Provides-Extra: pilot
Requires-Dist: pilotpy; extra == 'pilot'
Provides-Extra: scpoli
Requires-Dist: scarches>=0.5.1; extra == 'scpoli'
Provides-Extra: test
Requires-Dist: coverage; extra == 'test'
Requires-Dist: pytest; extra == 'test'
Requires-Dist: pytest-cov; extra == 'test'
Provides-Extra: wassersteintsne
Requires-Dist: wassersteintsne>=1.1; extra == 'wassersteintsne'
